subsample_fastas/__init__.py
subsample_fastas/__main__.py
subsample_fastas/cli.py
subsample_fastas/subsample_fastas.py
subsample_fastas/utils.py
subsample_fastas-0.0.0.dist-info/AUTHORS.md
subsample_fastas-0.0.0.dist-info/LICENSE
subsample_fastas-0.0.0.dist-info/METADATA
subsample_fastas-0.0.0.dist-info/WHEEL
subsample_fastas-0.0.0.dist-info/entry_points.txt
subsample_fastas-0.0.0.dist-info/top_level.txt
subsample_fastas-0.0.0.dist-info/RECORD
