Metadata-Version: 2.1
Name: subsample-fastas
Version: 0.0.0
Summary: Randomly alter fasta files by substracting a given % of genes in a genome (fasta) or in a (% of a) set of genomes 
Home-page: https://gitlab.inria.fr/pleiade/python-subsample_fastas
Author: Clémence Frioux
Author-email: clemence.frioux@inria.fr
License: CeCILL 2.1 Free Software License
Project-URL: Changelog, https://gitlab.inria.fr/pleiade/python-subsample_fastas/blob/master/CHANGELOG.md
Project-URL: Issue Tracker, https://gitlab.inria.fr/pleiade/python-subsample_fastas/issues
Platform: UNKNOWN
Classifier: Development Status :: 5 - Production/Stable
Classifier: Intended Audience :: Developers
Classifier: License :: OSI Approved :: CEA CNRS Inria Logiciel Libre License, version 2.1 (CeCILL-2.1)
Classifier: Operating System :: Unix
Classifier: Operating System :: POSIX
Classifier: Operating System :: Microsoft :: Windows
Classifier: Programming Language :: Python
Classifier: Programming Language :: Python :: 3.7
Classifier: Topic :: Utilities
Requires-Python: >=3.7
Requires-Dist: biopython (>=1.76)
Requires-Dist: pytest
